extract.py
helper/__init__.py
helper/helper.py
lit_extractor-0.2.6.dist-info/METADATA
lit_extractor-0.2.6.dist-info/WHEEL
lit_extractor-0.2.6.dist-info/entry_points.txt
lit_extractor-0.2.6.dist-info/top_level.txt
lit_extractor-0.2.6.dist-info/RECORD
