Metadata-Version: 2.1
Name: lit-extractor
Version: 0.2.6
Summary: A mini script to read a list of url and extract all the url's present in the webpage
Home-page: https://github.com/username/my_project
Author: Munish chandra jha
Author-email: mcj130101@gmail.com
License: MIT
Keywords: extractor,lit-extractor
Classifier: Programming Language :: Python :: 3
Classifier: License :: OSI Approved :: MIT License
Classifier: Operating System :: OS Independent
Requires-Python: >=3.6
Requires-Dist: click
Requires-Dist: fanficfare
Requires-Dist: tqdm
Requires-Dist: requests
Requires-Dist: rich
Requires-Dist: packaging
